niwrap_ants/ants/__init__.py
niwrap_ants/ants/add_noise_to_image.py
niwrap_ants/ants/ants_ai.py
niwrap_ants/ants/ants_align_origin.py
niwrap_ants/ants/ants_apply_transforms.py
niwrap_ants/ants/ants_apply_transforms_to_points.py
niwrap_ants/ants/ants_atropos_n4_sh.py
niwrap_ants/ants/ants_brain_extraction_sh.py
niwrap_ants/ants/ants_cortical_thickness_sh.py
niwrap_ants/ants/ants_intermodality_intrasubject_sh.py
niwrap_ants/ants/ants_introduction_sh.py
niwrap_ants/ants/ants_joint_fusion.py
niwrap_ants/ants/ants_joint_label_fusion_sh.py
niwrap_ants/ants/ants_joint_tensor_fusion.py
niwrap_ants/ants/ants_landmark_based_transform_initializer.py
niwrap_ants/ants/ants_motion_corr.py
niwrap_ants/ants/ants_motion_corr_diffusion_direction.py
niwrap_ants/ants/ants_motion_corr_stats.py
niwrap_ants/ants/ants_multivariate_template_construction2_sh.py
niwrap_ants/ants/ants_neuroimaging_battery.py
niwrap_ants/ants/ants_registration.py
niwrap_ants/ants/ants_registration_sy_n_sh.py
niwrap_ants/ants/ants_registration_sy_nquick_sh.py
niwrap_ants/ants/ants_slice_regularized_registration.py
niwrap_ants/ants/ants_transform_info.py
niwrap_ants/ants/antsintegrate_vector_field.py
niwrap_ants/ants/antsjacobian.py
niwrap_ants/ants/antsuse_deformation_field_to_get_affine_transform.py
niwrap_ants/ants/antsuse_landmark_images_to_get_affine_transform.py
niwrap_ants/ants/antsuse_landmark_images_to_get_bspline_displacement_field.py
niwrap_ants/ants/atropos.py
niwrap_ants/ants/convert_scalar_image_to_rgb.py
niwrap_ants/ants/convert_to_jpg.py
niwrap_ants/ants/convert_transform_file.py
niwrap_ants/ants/create_displacement_field.py
niwrap_ants/ants/create_dticohort.py
niwrap_ants/ants/create_tiled_mosaic.py
niwrap_ants/ants/create_warped_grid_image.py
niwrap_ants/ants/denoise_image.py
niwrap_ants/ants/extract_region_from_image.py
niwrap_ants/ants/extract_region_from_image_by_mask.py
niwrap_ants/ants/i_math.py
niwrap_ants/ants/image_intensity_statistics.py
niwrap_ants/ants/image_math.py
niwrap_ants-0.8.3.dist-info/WHEEL
niwrap_ants-0.8.3.dist-info/METADATA
niwrap_ants-0.8.3.dist-info/RECORD
